BCD_to7segm.v
module BCD(clk,Load,rst_asyn,Din,Q,Q_out);

input clk,Load,rst_asyn; 
input [3:0]Din;
output [3:0]Q;
reg [3:0]Q;
output [7:0] Q_out;      
reg [7:0] Q_out; 

always@ (posedge clk)begin
   if (!rst_asyn)
      Q <= 4'b0000; 
   else if(Load)
      Q <= Din;
   else if (Q == 9)
      Q <= 4'b0000;
   else
      Q <= Q +1;
end

always@(*) begin
     case (Q)
      4'b0000 : Q_out = 8'b11000000;
      4'b0001 : Q_out = 8'b11111001;
      4'b0010 : Q_out = 8'b10100100;
      4'b0011 : Q_out = 8'b10110000;
      4'b0100 : Q_out = 8'b10011001;
      4'b0101 : Q_out = 8'b10010010;
      4'b0110 : Q_out = 8'b10000010;
      4'b0111 : Q_out = 8'b11111000;
      4'b1000 : Q_out = 8'b10000000;
      4'b1001 : Q_out = 8'b10010000;
      4'b1010 : Q_out = 8'b10100000;
      4'b1011 : Q_out = 8'b10000011;
      4'b1100 : Q_out = 8'b10100111;
      4'b1101 : Q_out = 8'b10100001;
      4'b1110 : Q_out = 8'b10000100;
      4'b1111 : Q_out = 8'b11110001;
      default : Q_out = 8'b00000000;
     endcase
end
endmodule

BCD_to7segm_tb.v
`timescale 1ns/1ps //設定時間參數

module BCD_tb();

reg clk, rst_asyn,Load;
reg [3:0]Din;
wire [3:0]Q;
wire [7:0]Q_out;

parameter PERIOD = 20;
parameter real DUTY_CYCLE = 0.5;
parameter OFFSET = 0; 

initial
    begin   
        #OFFSET;
        forever
            begin
                clk = 1'b1;
                #(PERIOD-(PERIOD*DUTY_CYCLE)) clk = 1'b0;
                #(PERIOD*DUTY_CYCLE);
            end
        end
initial begin
    rst_asyn = 1'b0;
    Load = 1'b0;
    Din = 5;
    #5 rst_asyn = 1'b1;
    #350 Load = 1'b0;
    #20 Load = 1'b1;
    #10 Load = 1'b0;
    #200 rst_asyn = 1'b0;
    #50 rst_asyn = 1'b1;
    #1000 $finish;
end
initial
    begin
        $dumpfile("BCD_to7segm.vcd"); 
        $dumpvars(0,BCD_tb);  
    end
BCD BCD1_tb(
    .clk(clk),
    .Load(Load),
    .rst_asyn(rst_asyn),
    .Din(Din),
    .Q(Q),
    .Q_out(Q_out)
);
endmodule

BCD_to7segm.vcd
$date
	Wed May 04 20:57:54 2022
$end
$version
	Icarus Verilog
$end
$timescale
	1ps
$end
$scope module BCD_tb $end
$var wire 8 ! Q_out [7:0] $end
$var wire 4 " Q [3:0] $end
$var reg 4 # Din [3:0] $end
$var reg 1 $ Load $end
$var reg 1 % clk $end
$var reg 1 & rst_asyn $end
$scope module BCD1_tb $end
$var wire 4 ' Din [3:0] $end
$var wire 1 $ Load $end
$var wire 1 % clk $end
$var wire 1 & rst_asyn $end
$var reg 4 ( Q [3:0] $end
$var reg 8 ) Q_out [7:0] $end
$upscope $end
$upscope $end
$enddefinitions $end
#0
$dumpvars
b11000000 )
b0 (
b101 '
0&
1%
0$
b101 #
b0 "
b11000000 !
$end
#5000
1&
#10000
0%
#20000
b11111001 !
b11111001 )
b1 "
b1 (
1%
#30000
0%
#40000
b10100100 !
b10100100 )
b10 "
b10 (
1%
#50000
0%
#60000
b10110000 !
b10110000 )
b11 "
b11 (
1%
#70000
0%
#80000
b10011001 !
b10011001 )
b100 "
b100 (
1%
#90000
0%
#100000
b10010010 !
b10010010 )
b101 "
b101 (
1%
#110000
0%
#120000
b10000010 !
b10000010 )
b110 "
b110 (
1%
#130000
0%
#140000
b11111000 !
b11111000 )
b111 "
b111 (
1%
#150000
0%
#160000
b10000000 !
b10000000 )
b1000 "
b1000 (
1%
#170000
0%
#180000
b10010000 !
b10010000 )
b1001 "
b1001 (
1%
#190000
0%
#200000
b11000000 !
b11000000 )
b0 "
b0 (
1%
#210000
0%
#220000
b11111001 !
b11111001 )
b1 "
b1 (
1%
#230000
0%
#240000
b10100100 !
b10100100 )
b10 "
b10 (
1%
#250000
0%
#260000
b10110000 !
b10110000 )
b11 "
b11 (
1%
#270000
0%
#280000
b10011001 !
b10011001 )
b100 "
b100 (
1%
#290000
0%
#300000
b10010010 !
b10010010 )
b101 "
b101 (
1%
#310000
0%
#320000
b10000010 !
b10000010 )
b110 "
b110 (
1%
#330000
0%
#340000
b11111000 !
b11111000 )
b111 "
b111 (
1%
#350000
0%
#360000
b10000000 !
b10000000 )
b1000 "
b1000 (
1%
#370000
0%
#375000
1$
#380000
b10010010 !
b10010010 )
b101 "
b101 (
1%
#385000
0$
#390000
0%
#400000
b10000010 !
b10000010 )
b110 "
b110 (
1%
#410000
0%
#420000
b11111000 !
b11111000 )
b111 "
b111 (
1%
#430000
0%
#440000
b10000000 !
b10000000 )
b1000 "
b1000 (
1%
#450000
0%
#460000
b10010000 !
b10010000 )
b1001 "
b1001 (
1%
#470000
0%
#480000
b11000000 !
b11000000 )
b0 "
b0 (
1%
#490000
0%
#500000
b11111001 !
b11111001 )
b1 "
b1 (
1%
#510000
0%
#520000
b10100100 !
b10100100 )
b10 "
b10 (
1%
#530000
0%
#540000
b10110000 !
b10110000 )
b11 "
b11 (
1%
#550000
0%
#560000
b10011001 !
b10011001 )
b100 "
b100 (
1%
#570000
0%
#580000
b10010010 !
b10010010 )
b101 "
b101 (
1%
#585000
0&
#590000
0%
#600000
b11000000 !
b11000000 )
b0 "
b0 (
1%
#610000
0%
#620000
1%
#630000
0%
#635000
1&
#640000
b11111001 !
b11111001 )
b1 "
b1 (
1%
#650000
0%
#660000
b10100100 !
b10100100 )
b10 "
b10 (
1%
#670000
0%
#680000
b10110000 !
b10110000 )
b11 "
b11 (
1%
#690000
0%
#700000
b10011001 !
b10011001 )
b100 "
b100 (
1%
#710000
0%
#720000
b10010010 !
b10010010 )
b101 "
b101 (
1%
#730000
0%
#740000
b10000010 !
b10000010 )
b110 "
b110 (
1%
#750000
0%
#760000
b11111000 !
b11111000 )
b111 "
b111 (
1%
#770000
0%
#780000
b10000000 !
b10000000 )
b1000 "
b1000 (
1%
#790000
0%
#800000
b10010000 !
b10010000 )
b1001 "
b1001 (
1%
#810000
0%
#820000
b11000000 !
b11000000 )
b0 "
b0 (
1%
#830000
0%
#840000
b11111001 !
b11111001 )
b1 "
b1 (
1%
#850000
0%
#860000
b10100100 !
b10100100 )
b10 "
b10 (
1%
#870000
0%
#880000
b10110000 !
b10110000 )
b11 "
b11 (
1%
#890000
0%
#900000
b10011001 !
b10011001 )
b100 "
b100 (
1%
#910000
0%
#920000
b10010010 !
b10010010 )
b101 "
b101 (
1%
#930000
0%
#940000
b10000010 !
b10000010 )
b110 "
b110 (
1%
#950000
0%
#960000
b11111000 !
b11111000 )
b111 "
b111 (
1%
#970000
0%
#980000
b10000000 !
b10000000 )
b1000 "
b1000 (
1%
#990000
0%
#1000000
b10010000 !
b10010000 )
b1001 "
b1001 (
1%
#1010000
0%
#1020000
b11000000 !
b11000000 )
b0 "
b0 (
1%
#1030000
0%
#1040000
b11111001 !
b11111001 )
b1 "
b1 (
1%
#1050000
0%
#1060000
b10100100 !
b10100100 )
b10 "
b10 (
1%
#1070000
0%
#1080000
b10110000 !
b10110000 )
b11 "
b11 (
1%
#1090000
0%
#1100000
b10011001 !
b10011001 )
b100 "
b100 (
1%
#1110000
0%
#1120000
b10010010 !
b10010010 )
b101 "
b101 (
1%
#1130000
0%
#1140000
b10000010 !
b10000010 )
b110 "
b110 (
1%
#1150000
0%
#1160000
b11111000 !
b11111000 )
b111 "
b111 (
1%
#1170000
0%
#1180000
b10000000 !
b10000000 )
b1000 "
b1000 (
1%
#1190000
0%
#1200000
b10010000 !
b10010000 )
b1001 "
b1001 (
1%
#1210000
0%
#1220000
b11000000 !
b11000000 )
b0 "
b0 (
1%
#1230000
0%
#1240000
b11111001 !
b11111001 )
b1 "
b1 (
1%
#1250000
0%
#1260000
b10100100 !
b10100100 )
b10 "
b10 (
1%
#1270000
0%
#1280000
b10110000 !
b10110000 )
b11 "
b11 (
1%
#1290000
0%
#1300000
b10011001 !
b10011001 )
b100 "
b100 (
1%
#1310000
0%
#1320000
b10010010 !
b10010010 )
b101 "
b101 (
1%
#1330000
0%
#1340000
b10000010 !
b10000010 )
b110 "
b110 (
1%
#1350000
0%
#1360000
b11111000 !
b11111000 )
b111 "
b111 (
1%
#1370000
0%
#1380000
b10000000 !
b10000000 )
b1000 "
b1000 (
1%
#1390000
0%
#1400000
b10010000 !
b10010000 )
b1001 "
b1001 (
1%
#1410000
0%
#1420000
b11000000 !
b11000000 )
b0 "
b0 (
1%
#1430000
0%
#1440000
b11111001 !
b11111001 )
b1 "
b1 (
1%
#1450000
0%
#1460000
b10100100 !
b10100100 )
b10 "
b10 (
1%
#1470000
0%
#1480000
b10110000 !
b10110000 )
b11 "
b11 (
1%
#1490000
0%
#1500000
b10011001 !
b10011001 )
b100 "
b100 (
1%
#1510000
0%
#1520000
b10010010 !
b10010010 )
b101 "
b101 (
1%
#1530000
0%
#1540000
b10000010 !
b10000010 )
b110 "
b110 (
1%
#1550000
0%
#1560000
b11111000 !
b11111000 )
b111 "
b111 (
1%
#1570000
0%
#1580000
b10000000 !
b10000000 )
b1000 "
b1000 (
1%
#1590000
0%
#1600000
b10010000 !
b10010000 )
b1001 "
b1001 (
1%
#1610000
0%
#1620000
b11000000 !
b11000000 )
b0 "
b0 (
1%
